covid_advisor/__init__.py
covid_advisor/__main__.py
covid_advisor/app/__init__.py
covid_advisor/app/advisory_flask.py
covid_advisor/app/app_testrun.py
covid_advisor/app/covid_stats.py
covid_advisor/app/security.py
covid_advisor/app/user_database.py
covid_advisory-0.0.4.dist-info/METADATA
covid_advisory-0.0.4.dist-info/WHEEL
covid_advisory-0.0.4.dist-info/top_level.txt
covid_advisory-0.0.4.dist-info/RECORD
