Metadata-Version: 2.1
Name: covid-advisory
Version: 0.0.4
Summary: A small example package
Home-page: https://github.com/pypa/sampleproject
Author: Example Author
Author-email: author@example.com
License: UNKNOWN
Platform: UNKNOWN
Classifier: Programming Language :: Python :: 3
Classifier: License :: OSI Approved :: MIT License
Classifier: Operating System :: OS Independent
Requires-Python: >=3.6
Requires-Dist: flask
Requires-Dist: flask-jwt
Requires-Dist: Cython
Requires-Dist: flask-restful
Requires-Dist: requests
Requires-Dist: datetime
Requires-Dist: numpy
Requires-Dist: mysql-connector
